dndbuddy/__init__.py
dndbuddy/constants.py
dndbuddy/main.py
dndbuddy-0.0.1.dist-info/METADATA
dndbuddy-0.0.1.dist-info/WHEEL
dndbuddy-0.0.1.dist-info/entry_points.txt
dndbuddy-0.0.1.dist-info/top_level.txt
dndbuddy-0.0.1.dist-info/RECORD
