Metadata-Version: 2.1
Name: dndbuddy
Version: 0.0.1
Summary: It's DnDBuddy!
Home-page: https://github.com/MattCCS/DnDBuddy
Author: Matt Cotton
Author-email: matthewcotton.cs@gmail.com
License: UNKNOWN
Platform: UNKNOWN
Classifier: Programming Language :: Python :: 3
Requires-Dist: dndbuddy-core
